{
    "contributors": [],
    "creation_date": "2018/10/26 18:00:23.314890 GMT-4",
    "_uid": "4e108e2124e24a26a08e6432dd0cfd51",
    "expirationDate": "None",
    "_content_type_id": "text/plain",
    "id": "nulla-magna-porta-nulla-a-mattis-curae-vestibulum-pharetra-urna-natoque.",
    "subject": [],
    "modification_date": "2018/10/26 18:00:23.359020 GMT-4",
    "title": "Nulla magna porta nulla a mattis curae vestibulum pharetra urna natoque.",
    "_ac_local_roles": {
        "admin": [
            "Owner"
        ]
    },
    "_content_type_language": "text/plain",
    "_defaultpage": "",
    "location": "Metus porta donec nascetur cum quis cras elit.",
    "_content_type_title": "text/plain",
    "excludeFromNav": false,
    "_atbrefs": {},
    "_type": "Link",
    "description": "Massa proin mauris pellentesque lacinia felis. Lacus velit facilisi adipiscing mauris nec ve mollis quisque mattis. Massa lacus aptent erat. Magna nulla volutpat justo venenatis pharetra. Metus magna condimentum duis. Augue class velit a potenti in nisl dis porta feugiat aenean ultricies faucibus. Fusce risus placerat. Velit morbi justo cubilia arcu. Nulla felis congue. Velit fames. Felis augue ultrices velit porttitor. Lorem netus diam nunc eni. Dolor donec dictum pulvinar odio cubilia mi. Purus netus lectus torquent nisi accumsan montes sociis nunc per. Vitae augue diam quisque odio ve diam nunc etiam ac. Fames lorem per nisl egestas eget velit egestas rhoncus duis nulla proin netus fusce scelerisque sociosqu.",
    "_atrefs": {},
    "_layout": "link_redirect_view",
    "_workflow_history": {
        "simple_publication_workflow": [
            {
                "action": null,
                "review_state": "private",
                "actor": "admin",
                "comments": "",
                "time": "2018/10/26 18:00:23.318098 GMT-4"
            },
            {
                "action": "publish",
                "review_state": "published",
                "actor": "admin",
                "comments": "",
                "time": "2018/10/26 18:00:23.355113 GMT-4"
            }
        ]
    },
    "_content_type_rights": "text/plain",
    "_directly_provided": [],
    "_content_type_remoteUrl": "text/plain",
    "_classname": "ATLink",
    "_userdefined_roles": [],
    "_content_type": "text/plain",
    "_id": "nulla-magna-porta-nulla-a-mattis-curae-vestibulum-pharetra-urna-natoque.",
    "remoteUrl": "Felis%20magna%20donec%20porta%20etiam%20risus.",
    "effectiveDate": "None",
    "language": "en",
    "rights": "Lorem fusce nisi primis rhoncus euismod orci. Dolor lacus donec sociosqu. Purus velit fusce non pede dis. Justo fames. Proin velit mauris netus vestibulum lobortis diam magnis vivamus elit nibh integer. Nulla proin rutrum adipiscing felis. Justo metus erat dis sodales ad. Purus class. Netus augue leo erat mattis dictum facilisis inceptos dictum libero in semper nunc. Etiam metus proin scelerisque eleifend. Etiam justo curae hymenaeos parturient. Porta proin cursus feugiat viverra. Ipsum magna interdum ut fames sollicitudin porta. Lacus fusce primis montes habitant leo. Augue etiam. Class nulla metus netus sem elit nunc egestas. Ipsum curae nulla convallis cubilia nam ac. Felis fames tincidunt sit mus sed in. Class felis eget ut etiam ve eget nunc proin blandit.",
    "_content_type_description": "text/plain",
    "_owner": "admin",
    "_content_type_location": "text/plain",
    "_permissions": {
        "Modify portal content": {
            "acquire": false,
            "roles": [
                "Editor",
                "Manager",
                "Owner",
                "Site Administrator"
            ]
        },
        "Access contents information": {
            "acquire": false,
            "roles": [
                "Anonymous"
            ]
        },
        "View": {
            "acquire": false,
            "roles": [
                "Anonymous"
            ]
        }
    },
    "_properties": [
        [
            "title",
            "Nulla magna porta nulla a mattis curae vestibulum pharetra urna natoque.",
            "string"
        ]
    ],
    "allowDiscussion": false,
    "_gopip": 56,
    "creators": [
        "admin"
    ],
    "_path": "/Plone/about/lacus-purus-sit-augue-facilisis-ultricies-pede./metus-augue-platea-donec-fames-inceptos-non-ut-fermentum-ipsum./nulla-magna-porta-nulla-a-mattis-curae-vestibulum-pharetra-urna-natoque."
}