{
    "tableContents": false,
    "_content_type_text": "text/html",
    "text": "<h1>Si longus, levis.</h1>\n\n<p>Lorem ipsum dolor sit amet, consectetur adipiscing elit. Qua tu etiam inprudens utebare non numquam. Duo Reges: constructio interrete. Quamquam id quidem licebit iis existimare, qui legerint. Si longus, levis dictata sunt. <a href='http://loripsum.net/' target='_blank'>Hoc ipsum elegantius poni meliusque potuit.</a> Ut pulsi recurrant? Id est enim, de quo quaerimus. </p>\n\n<ol>\n\t<li>Miserum hominem! Si dolor summum malum est, dici aliter non potest.</li>\n\t<li>Ut scias me intellegere, primum idem esse dico voluptatem, quod ille don.</li>\n\t<li>Haec para/doca illi, nos admirabilia dicamus.</li>\n</ol>\n\n\n<dl>\n\t<dt><dfn>Sedulo, inquam, faciam.</dfn></dt>\n\t<dd>At ille non pertimuit saneque fidenter: Istis quidem ipsis verbis, inquit;</dd>\n\t<dt><dfn>Ille incendat?</dfn></dt>\n\t<dd>Mihi quidem Homerus huius modi quiddam vidisse videatur in iis, quae de Sirenum cantibus finxerit.</dd>\n\t<dt><dfn>Ut pulsi recurrant?</dfn></dt>\n\t<dd>Igitur neque stultorum quisquam beatus neque sapientium non beatus.</dd>\n</dl>\n\n\n<p>Minime vero, inquit ille, consentit. Sed hoc sane concedamus. Conferam avum tuum Drusum cum C. Mihi, inquam, qui te id ipsum rogavi? Sed ad illum redeo. <a href='http://loripsum.net/' target='_blank'>Quae similitudo in genere etiam humano apparet.</a> </p>\n\n<ul>\n\t<li>Huic ego, si negaret quicquam interesse ad beate vivendum quali uteretur victu, concederem, laudarem etiam;</li>\n\t<li>Ut in geometria, prima si dederis, danda sunt omnia.</li>\n\t<li>Quod non faceret, si in voluptate summum bonum poneret.</li>\n\t<li>Quae fere omnia appellantur uno ingenii nomine, easque virtutes qui habent, ingeniosi vocantur.</li>\n</ul>\n\n\n<p><a href='http://loripsum.net/' target='_blank'>Primum quid tu dicis breve?</a> <a href='http://loripsum.net/' target='_blank'>Ut pulsi recurrant?</a> Simus igitur contenti his. Quae similitudo in genere etiam humano apparet. Quid adiuvas? Quare ad ea primum, si videtur; </p>\n\n",
    "creation_date": "2018/10/26 18:03:36.453981 GMT-4",
    "_uid": "df8983d7e3394675901416bb23585fdf",
    "expirationDate": "None",
    "_content_type_id": "text/plain",
    "query": [],
    "_atbrefs": {},
    "id": "donec-dolor-amet-ut-nisl-duis-parturient-nostra-sem.",
    "subject": [],
    "_content_type_sort_on": "text/plain",
    "contributors": [],
    "effectiveDate": "None",
    "title": "Donec dolor amet ut nisl duis parturient nostra sem.",
    "_ac_local_roles": {
        "admin": [
            "Owner"
        ]
    },
    "sort_on": "Class velit taciti curae cum quam non.",
    "_content_type_language": "text/plain",
    "_defaultpage": "",
    "location": "Purus magna tortor eros condimentum sit litora id ac libero sit parturient lacus laoreet.",
    "_content_type_title": "text/plain",
    "excludeFromNav": false,
    "presentation": false,
    "_type": "Collection",
    "description": "Lorem nulla facilisis massa. Ipsum magna congue torquent conubia aliquam. Curae massa vivamus faucibus felis nunc in. Nulla morbi vitae eget cras sit ve morbi ad elementum purus conubia eu penatibus. Risus etiam fames fusce amet torquent velit ve. Fames felis sed pede vestibulum eros risus. Fusce felis bibendum curabitur bibendum sapien auctor felis mus fermentum faucibus massa at lacus ut ligula. Ipsum vitae iaculis enim sagittis. Augue magna enim dis. Risus purus ipsum ultrices dolor luctus pretium fringilla sagittis fusce tellus. Magna vitae. Dolor curae montes massa hac massa convallis etiam quam feugiat neque est sed. Justo metus vehicula non augue vel nullam eros duis tempor conubia in nullam sollicitudin imperdiet. Class etiam duis suspendisse rhoncus class. Ipsum risus. Neque proin tempor enim ve erat posuere lacinia dictum et convallis fermentum odio taciti nec luctus. Purus etiam habitant felis quam ante nec urna. Nulla morbi. Donec fusce duis ve sollicitudin. Class massa natoque aliquet auctor.",
    "_atrefs": {},
    "_layout": "standard_view",
    "_workflow_history": {
        "simple_publication_workflow": [
            {
                "action": null,
                "review_state": "private",
                "actor": "admin",
                "comments": "",
                "time": "2018/10/26 18:03:36.463282 GMT-4"
            },
            {
                "action": "publish",
                "review_state": "published",
                "actor": "admin",
                "comments": "",
                "time": "2018/10/26 18:03:37.092423 GMT-4"
            }
        ]
    },
    "_content_type_rights": "text/plain",
    "_directly_provided": [],
    "_classname": "Collection",
    "sort_reversed": true,
    "banner": "<h1>Si stante, hoc natura videlicet vult, salvam esse se, quod concedimus;</h1>\n\n<p>Lorem ipsum dolor sit amet, consectetur adipiscing elit. Respondeat totidem verbis. Itaque ad tempus ad Pisonem omnes. Haec quo modo conveniant, non sane intellego. Quamquam te quidem video minime esse deterritum. </p>\n\n<dl>\n\t<dt><dfn>Quod equidem non reprehendo;</dfn></dt>\n\t<dd>Quod non faceret, si in voluptate summum bonum poneret.</dd>\n\t<dt><dfn>Ut pulsi recurrant?</dfn></dt>\n\t<dd>Oratio me istius philosophi non offendit;</dd>\n</dl>\n\n\n<p>Efficiens dici potest. Sed ille, ut dixi, vitiose. Quae diligentissime contra Aristonem dicuntur a Chryippo. Num quid tale Democritus? Quod cum dixissent, ille contra. Sedulo, inquam, faciam. </p>\n\n<ol>\n\t<li>Addidisti ad extremum etiam indoctum fuisse.</li>\n\t<li>Quod cum dixissent, ille contra.</li>\n</ol>\n\n\n<ul>\n\t<li>Tum Torquatus: Prorsus, inquit, assentior;</li>\n\t<li>Sextilio Rufo, cum is rem ad amicos ita deferret, se esse heredem Q.</li>\n\t<li>Quia voluptatem hanc esse sentiunt omnes, quam sensus accipiens movetur et iucunditate quadam perfunditur.</li>\n\t<li>Utinam quidem dicerent alium alio beatiorem! Iam ruinas videres.</li>\n\t<li>Cupit enim d\u00edcere nihil posse ad beatam vitam deesse sapienti.</li>\n</ul>\n\n\n<p>Quis hoc dicit? Duo Reges: constructio interrete. Ac tamen hic mallet non dolere. Sed quot homines, tot sententiae; Nemo igitur esse beatus potest. Istic sum, inquit. </p>\n\n",
    "_userdefined_roles": [],
    "modification_date": "2018/10/26 18:03:37.097241 GMT-4",
    "_content_type": "text/html",
    "_id": "donec-dolor-amet-ut-nisl-duis-parturient-nostra-sem.",
    "language": "en",
    "_content_type_banner": "text/html",
    "rights": "Risus velit nec leo vulputate pede vel dolor rutrum. Donec dolor lobortis nec nisi. Neque massa. Dolor curae justo diam sapien potenti eros. Augue ipsum curae tellus ullamcorper neque malesuada facilisi mauris. Vitae lorem morbi molestie et mattis mus adipiscing hendrerit fusce ut vitae eget a curae dapibus tempor at rutrum. Massa vitae sociis erat. Class augue a primis elit enim vitae aliquam vehicula vitae ligula lorem quisque varius. Proin vitae nibh integer cursus sed nullam. Risus ipsum nibh auctor ut accumsan lacus habitasse venenatis dolor facilisi. Proin fames. Nulla proin tellus. Porta fames. Etiam proin auctor curae dolor laoreet. Lorem etiam.",
    "b_size": 30,
    "customViewFields": [
        "Title",
        "Creator",
        "Type",
        "ModificationDate"
    ],
    "_content_type_description": "text/plain",
    "_owner": "admin",
    "_content_type_location": "text/plain",
    "limit": 1000,
    "_permissions": {
        "Change portal events": {
            "acquire": false,
            "roles": [
                "Editor",
                "Manager",
                "Owner",
                "Site Administrator"
            ]
        },
        "Modify portal content": {
            "acquire": false,
            "roles": [
                "Editor",
                "Manager",
                "Owner",
                "Site Administrator"
            ]
        },
        "Access contents information": {
            "acquire": false,
            "roles": [
                "Anonymous"
            ]
        },
        "View": {
            "acquire": false,
            "roles": [
                "Anonymous"
            ]
        }
    },
    "_properties": [
        [
            "title",
            "Donec dolor amet ut nisl duis parturient nostra sem.",
            "string"
        ]
    ],
    "allowDiscussion": false,
    "_gopip": 74,
    "creators": [
        "admin"
    ],
    "_path": "/Plone/about/lacus-purus-sit-augue-facilisis-ultricies-pede./donec-dolor-amet-ut-nisl-duis-parturient-nostra-sem."
}