{
    "tableContents": false,
    "_content_type_text": "text/html",
    "text": "<h1>Hos contra singulos dici est melius.</h1>\n\n<p>Lorem ipsum dolor sit amet, consectetur adipiscing elit. <a href='http://loripsum.net/' target='_blank'>Eam stabilem appellas.</a> Beatus sibi videtur esse moriens. Nunc haec primum fortasse audientis servire debemus. Duo Reges: constructio interrete. Ergo illi intellegunt quid Epicurus dicat, ego non intellego? </p>\n\n<ul>\n\t<li>Quod autem in homine praestantissimum atque optimum est, id deseruit.</li>\n\t<li>Expressa vero in iis aetatibus, quae iam confirmatae sunt.</li>\n\t<li>Quia nec honesto quic quam honestius nec turpi turpius.</li>\n\t<li>Ergo hoc quidem apparet, nos ad agendum esse natos.</li>\n\t<li>Potius inflammat, ut coercendi magis quam dedocendi esse videantur.</li>\n\t<li>Inde igitur, inquit, ordiendum est.</li>\n</ul>\n\n\n<ol>\n\t<li>Id enim volumus, id contendimus, ut officii fructus sit ipsum officium.</li>\n\t<li>Eaedem enim utilitates poterunt eas labefactare atque pervertere.</li>\n\t<li>Quamquam te quidem video minime esse deterritum.</li>\n\t<li>Itaque hoc frequenter dici solet a vobis, non intellegere nos, quam dicat Epicurus voluptatem.</li>\n</ol>\n\n\n<p>Nam, ut sint illa vendibiliora, haec uberiora certe sunt. An potest cupiditas finiri? </p>\n\n<dl>\n\t<dt><dfn>Ita credo.</dfn></dt>\n\t<dd>Quid ergo aliud intellegetur nisi uti ne quae pars naturae neglegatur?</dd>\n\t<dt><dfn>Sit sane ista voluptas.</dfn></dt>\n\t<dd>Sed eum qui audiebant, quoad poterant, defendebant sententiam suam.</dd>\n</dl>\n\n\n<p><a href='http://loripsum.net/' target='_blank'>Tecum optime, deinde etiam cum mediocri amico.</a> Que Manilium, ab iisque M. Conferam tecum, quam cuique verso rem subicias; <a href='http://loripsum.net/' target='_blank'>Quae similitudo in genere etiam humano apparet.</a> </p>\n\n",
    "creation_date": "2018/10/26 18:04:40.444585 GMT-4",
    "_uid": "e59269b34ce74d089d2275329b555534",
    "expirationDate": "None",
    "_content_type_id": "text/plain",
    "query": [],
    "_atbrefs": {},
    "id": "vitae-etiam-faucibus.",
    "subject": [],
    "_content_type_sort_on": "text/plain",
    "contributors": [],
    "effectiveDate": "None",
    "title": "Vitae etiam faucibus.",
    "_ac_local_roles": {
        "admin": [
            "Owner"
        ]
    },
    "sort_on": "Lacus magna mus cubilia lobortis in vitae ad ornare.",
    "_content_type_language": "text/plain",
    "_defaultpage": "",
    "location": "Risus magna metus magna metus a tortor eget phasellus magna.",
    "_content_type_title": "text/plain",
    "excludeFromNav": false,
    "presentation": false,
    "_type": "Collection",
    "description": "Neque risus. Porta dolor pharetra fringilla suscipit vitae id nibh quis pede quam tortor posuere. Velit magna curabitur est felis velit lorem potenti. Dolor augue. Metus ipsum morbi a pretium ad neque. Magna donec a pede adipiscing ad elementum eget quam nam a mollis. Dolor magna velit felis vel odio nam id mattis taciti metus nullam scelerisque curae imperdiet magnis proin scelerisque pharetra metus diam conubia. Massa felis. Curae netus urna vivamus orci. Felis nulla vitae platea eget orci enim gravida ridiculus. Neque purus scelerisque ante quam class habitasse vehicula diam. Justo class luctus pulvinar vulputate vehicula fusce in fermentum lacus curabitur aenean. Purus fusce libero. Augue lorem. Vitae morbi class tempus aenean ut arcu mi pellentesque feugiat vitae cras.",
    "_atrefs": {},
    "_layout": "standard_view",
    "_workflow_history": {
        "simple_publication_workflow": [
            {
                "action": null,
                "review_state": "private",
                "actor": "admin",
                "comments": "",
                "time": "2018/10/26 18:04:40.450964 GMT-4"
            },
            {
                "action": "publish",
                "review_state": "published",
                "actor": "admin",
                "comments": "",
                "time": "2018/10/26 18:04:41.057026 GMT-4"
            }
        ]
    },
    "_content_type_rights": "text/plain",
    "_directly_provided": [],
    "_classname": "Collection",
    "sort_reversed": true,
    "banner": "<h1>Quid enim me prohiberet Epicureum esse, si probarem, quae ille diceret?</h1>\n\n<p>Lorem ipsum dolor sit amet, consectetur adipiscing elit. Cur post Tarentum ad Archytam? Illi enim inter se dissentiunt. Non laboro, inquit, de nomine. <a href='http://loripsum.net/' target='_blank'>Duo Reges: constructio interrete.</a> Eadem nunc mea adversum te oratio est. </p>\n\n<ul>\n\t<li>Satisne vobis videor pro meo iure in vestris auribus commentatus?</li>\n\t<li>Itaque haec cum illis est dissensio, cum Peripateticis nulla sane.</li>\n\t<li>Ergo, inquit, tibi Q.</li>\n\t<li>Quae cum dixisset paulumque institisset, Quid est?</li>\n\t<li>Quid, quod homines infima fortuna, nulla spe rerum gerendarum, opifices denique delectantur historia?</li>\n\t<li>Utrum igitur tibi litteram videor an totas paginas commovere?</li>\n</ul>\n\n\n<dl>\n\t<dt><dfn>Venit ad extremum;</dfn></dt>\n\t<dd>Virtutibus igitur rectissime mihi videris et ad consuetudinem nostrae orationis vitia posuisse contraria.</dd>\n\t<dt><dfn>Qui convenit?</dfn></dt>\n\t<dd>Sed tamen omne, quod de re bona dilucide dicitur, mihi praeclare dici videtur.</dd>\n\t<dt><dfn>Stoici scilicet.</dfn></dt>\n\t<dd>Etiam inchoatum, ut, si iuste depositum reddere in recte factis sit, in officiis ponatur depositum reddere;</dd>\n\t<dt><dfn>Ita prorsus, inquam;</dfn></dt>\n\t<dd>Polemoni et iam ante Aristoteli ea prima visa sunt, quae paulo ante dixi.</dd>\n\t<dt><dfn>Proclivi currit oratio.</dfn></dt>\n\t<dd>Ut in geometria, prima si dederis, danda sunt omnia.</dd>\n</dl>\n\n\n<ol>\n\t<li>Tu vero, inquam, ducas licet, si sequetur;</li>\n\t<li>Innumerabilia dici possunt in hanc sententiam, sed non necesse est.</li>\n\t<li>Miserum hominem! Si dolor summum malum est, dici aliter non potest.</li>\n\t<li>Non enim, si omnia non sequebatur, idcirco non erat ortus illinc.</li>\n\t<li>Non potes, nisi retexueris illa.</li>\n\t<li>Eorum enim est haec querela, qui sibi cari sunt seseque diligunt.</li>\n</ol>\n\n\n<h2>Paulum, cum regem Persem captum adduceret, eodem flumine invectio?</h2>\n\n<p>Suo genere perveniant ad extremum; Cur tantas regiones barbarorum pedibus obiit, tot maria transmisit? Huius, Lyco, oratione locuples, rebus ipsis ielunior. Restatis igitur vos; </p>\n\n<p>Quod ea non occurrentia fingunt, vincunt Aristonem; Sed virtutem ipsam inchoavit, nihil amplius. Re mihi non aeque satisfacit, et quidem locis pluribus. Quamquam id quidem licebit iis existimare, qui legerint. Quid sequatur, quid repugnet, vident. </p>\n\n",
    "_userdefined_roles": [],
    "modification_date": "2018/10/26 18:04:41.061282 GMT-4",
    "_content_type": "text/html",
    "_id": "vitae-etiam-faucibus.",
    "language": "en",
    "_content_type_banner": "text/html",
    "rights": "Dolor vitae arcu ipsum magnis lacus felis molestie curae ve tristique netus. Risus lacus condimentum pede phasellus leo faucibus a dictumst mus nisi felis condimentum. Netus fames nec adipiscing ac congue. Purus etiam suspendisse sagittis felis ad. Nulla dolor mus dictum mi. Ipsum neque sagittis morbi rhoncus ornare et arcu habitasse. Ipsum neque aenean nostra porttitor ve nisi lorem diam. Lorem donec enim mus enim urna vestibulum montes ve placerat massa purus. Dolor curae. Risus vitae taciti nibh porttitor sapien vel. Justo augue est vestibulum adipiscing at porttitor vestibulum lacinia. Risus porta. Magna netus taciti ut. Fames etiam suspendisse urna amet ultricies mollis faucibus ante. Porta etiam suspendisse eni ut platea inceptos. Fusce morbi libero lectus praesent nisl feugiat curabitur amet suspendisse. Fusce risus leo magna tortor.",
    "b_size": 30,
    "customViewFields": [
        "Title",
        "Creator",
        "Type",
        "ModificationDate"
    ],
    "_content_type_description": "text/plain",
    "_owner": "admin",
    "_content_type_location": "text/plain",
    "limit": 1000,
    "_permissions": {
        "Change portal events": {
            "acquire": false,
            "roles": [
                "Editor",
                "Manager",
                "Owner",
                "Site Administrator"
            ]
        },
        "Modify portal content": {
            "acquire": false,
            "roles": [
                "Editor",
                "Manager",
                "Owner",
                "Site Administrator"
            ]
        },
        "Access contents information": {
            "acquire": false,
            "roles": [
                "Anonymous"
            ]
        },
        "View": {
            "acquire": false,
            "roles": [
                "Anonymous"
            ]
        }
    },
    "_properties": [
        [
            "title",
            "Vitae etiam faucibus.",
            "string"
        ]
    ],
    "allowDiscussion": false,
    "_gopip": 72,
    "creators": [
        "admin"
    ],
    "_path": "/Plone/about/fames-neque-nostra-habitasse./risus-velit-curae./vitae-etiam-faucibus."
}